darth_d/__init__.py
darth_d/_create.py
darth_d/_napari_plugin.py
darth_d/_replace.py
darth_d/_utilities.py
darth_d/_vary.py
darth_d-0.4.0.dist-info/LICENSE
darth_d-0.4.0.dist-info/METADATA
darth_d-0.4.0.dist-info/WHEEL
darth_d-0.4.0.dist-info/entry_points.txt
darth_d-0.4.0.dist-info/top_level.txt
darth_d-0.4.0.dist-info/RECORD
