Metadata-Version: 2.1
Name: darth-d
Version: 0.4.0
Summary: A simple to use image generator based on OpenAIs DALL-E
Home-page: https://github.com/haesleinhuepf/darth-d/
Author: Robert Haase
Author-email: robert.haase@uni-leipzig.de
License: BSD-3-Clause
Project-URL: Bug Tracker, https://github.com/haesleinhuepf/darth-d/issues
Project-URL: Documentation, https://github.com/haesleinhuepf/darth-d/
Project-URL: Source Code, https://github.com/haesleinhuepf/darth-d
Project-URL: User Support, https://forum.image.sc/
Classifier: Framework :: napari
Classifier: License :: OSI Approved :: BSD License
Classifier: Topic :: Scientific/Engineering :: Image Processing
Classifier: Topic :: Scientific/Engineering :: Information Analysis
Classifier: Programming Language :: Python
Classifier: Programming Language :: Python :: 3
Classifier: Programming Language :: Python :: 3.7
Classifier: Programming Language :: Python :: 3.8
Classifier: Programming Language :: Python :: 3.9
Classifier: Operating System :: OS Independent
Requires-Python: >=3.8
License-File: LICENSE
Requires-Dist: openai >=1.2.0
Requires-Dist: Pillow
Requires-Dist: numpy
Requires-Dist: stackview >=0.7.1
